_ic_candid_core/__init__.py
_ic_candid_core/_ic_candid_core.abi3.so
ic_candid_parser-0.1.0.dist-info/METADATA
ic_candid_parser-0.1.0.dist-info/WHEEL
ic_candid_parser-0.1.0.dist-info/RECORD
