Metadata-Version: 2.4
Name: ic-candid-parser
Version: 0.1.0
Classifier: Programming Language :: Rust
Classifier: Programming Language :: Python :: Implementation :: CPython
Classifier: Programming Language :: Python :: Implementation :: PyPy
Summary: Rust extension for parsing Candid DID files (part of icp-py-core)
Requires-Python: >=3.8
